LICENSE
MANIFEST.in
README.md
setup.py
data/container.json
data/request.json
data/stitch.json
graph_stitcher.egg-info/PKG-INFO
graph_stitcher.egg-info/SOURCES.txt
graph_stitcher.egg-info/dependency_links.txt
graph_stitcher.egg-info/top_level.txt
stitcher/__init__.py
stitcher/bidding.py
stitcher/evolutionary.py
stitcher/iterative_repair.py
stitcher/stitch.py
stitcher/validators.py
stitcher/vis.py