Metadata-Version: 1.1
Name: graph-stitcher
Version: 0.0.18
Summary: This tool is a little framework to determine possiblemerges between two graphs based on a set of requiredadditional relationships (aka as stitches / edges).
Home-page: https://github.com/tmetsch/graph_stitcher
Author: Thijs Metsch
Author-email: UNKNOWN
License: MIT
Keywords: graph stitching algorithms framework
Platform: UNKNOWN
Classifier: Development Status :: 3 - Alpha
Classifier: License :: OSI Approved :: MIT License
Classifier: Topic :: Scientific/Engineering
Classifier: Topic :: Utilities
